settings_parser/__init__.py
settings_parser/settings.py
settings_parser/settings_config.py
settings_parser/util.py
settings_parser/value.py
settings_parser-1.3.2.dist-info/DESCRIPTION.rst
settings_parser-1.3.2.dist-info/METADATA
settings_parser-1.3.2.dist-info/RECORD
settings_parser-1.3.2.dist-info/WHEEL
settings_parser-1.3.2.dist-info/metadata.json
settings_parser-1.3.2.dist-info/top_level.txt
