Metadata-Version: 1.1
Name: settings_parser
Version: 1.3.2
Summary: settings_parser: Load, parse and validate user settings
Home-page: https://github.com/pedvide/settings_parser
Author: Pedro Villanueva Delgado
Author-email: pedvide@gmail.com
License: MIT
Keywords: settings configuration config validator parser
Platform: UNKNOWN
Classifier: Development Status :: 3 - Alpha
Classifier: Intended Audience :: Developers
Classifier: Topic :: Software Development :: User Interfaces
Classifier: Operating System :: MacOS :: MacOS X
Classifier: Operating System :: Microsoft :: Windows
Classifier: Operating System :: POSIX
Classifier: License :: OSI Approved :: MIT License
Classifier: Programming Language :: Python :: 3.6
